{
    "date": "2024-11-08 16:33:20.671946",
    "debug": {
        "coding_deg": 44.27057806693136,
        "temporal_deg": 0.0,
        "upscaling_deg": 16.767114378630264
    },
    "model": "bitstream_mode0",
    "per_second": [
        2.371234827349252,
        2.371234827349252,
        2.371234827349252,
        2.371234827349252,
        2.371234827349252,
        2.371234827349252,
        2.371234827349252,
        2.371234827349252,
        2.371234827349252,
        2.371234827349252
    ],
    "per_sequence": 2.371234827349252,
    "version": "0.1.0",
    "video_basename": "AVT-Faces_lightingLoop__V8-0019_720p_crf22_hevc.mkv",
    "video_full_path": "../../avt-bigdata/co_worker/rakesh/4k_viewing_distance_2/videosegments/chosen/AVT-Faces_lightingLoop__V8-0019_720p_crf22_hevc.mkv"
}