{
    "date": "2024-11-08 16:40:33.109898",
    "debug": {
        "coding_deg": 30.29286094509895,
        "temporal_deg": 0.0,
        "upscaling_deg": 0.0
    },
    "model": "bitstream_mode1",
    "per_second": [
        4.288239960635578,
        4.288239960635578,
        4.288239960635578,
        4.288239960635578,
        4.288239960635578,
        4.288239960635578,
        4.288239960635578,
        4.288239960635578
    ],
    "per_sequence": 4.288239960635578,
    "version": "0.1.0",
    "video_basename": "Moment_of_Intensity_8s_2160p_crf22_hevc.mkv",
    "video_full_path": "../../avt-bigdata/co_worker/rakesh/4k_viewing_distance_2/videosegments/chosen/Moment_of_Intensity_8s_2160p_crf22_hevc.mkv"
}