{
    "date": "2025-01-20 10:47:46.845179",
    "debug": {
        "coding_deg": 29.357198513654794,
        "temporal_deg": 0.0,
        "upscaling_deg": 0.0
    },
    "model": "bitstream_mode1",
    "per_second": [
        4.342000820443545,
        4.342000820443545,
        4.342000820443545,
        4.342000820443545,
        4.342000820443545,
        4.342000820443545,
        4.342000820443545,
        4.342000820443545,
        4.342000820443545,
        4.342000820443545
    ],
    "per_sequence": 4.342000820443545,
    "version": "0.1.0",
    "video_basename": "BunnyAnimation_15000k_2160_hevc.mkv",
    "video_full_path": "../../../avt-bigdata/co_worker/rakesh/4k_viewing_distance/encoded_hevc/BunnyAnimation_15000k_2160_hevc.mkv"
}