{
    "date": "2025-01-20 10:47:15.092861",
    "debug": {
        "coding_deg": 38.08446939060693,
        "temporal_deg": 0.0,
        "upscaling_deg": 16.767114378630264
    },
    "model": "bitstream_mode1",
    "per_second": [
        2.749438092510357,
        2.749438092510357,
        2.749438092510357,
        2.749438092510357,
        2.749438092510357,
        2.749438092510357,
        2.749438092510357,
        2.749438092510357
    ],
    "per_sequence": 2.749438092510357,
    "version": "0.1.0",
    "video_basename": "Giftmord-SDR_8s_11_3840x2160_1000k_720_hevc.mkv",
    "video_full_path": "../../../avt-bigdata/co_worker/rakesh/4k_viewing_distance/encoded_hevc/Giftmord-SDR_8s_11_3840x2160_1000k_720_hevc.mkv"
}