{
    "date": "2024-10-03 11:19:03.418283",
    "debug": {
        "baseline": 3.490974452894264,
        "coding_deg": 43.239888818062745,
        "rf_pred": 2.9357658292185964,
        "temporal_deg": 0.0,
        "upscaling_deg": 0.0
    },
    "features": {
        "0.0_quantil_StdDev_MotionX_non-i": 0.0031622776601683794,
        "1.0_quantil_FrameSize": 55207.0,
        "Bitrate": 579.2978515625,
        "Framerate": 60.0,
        "Resolution": 8294400.0,
        "h264": 0.0,
        "h264_10bit": 0.0,
        "hevc": 1.0,
        "hevc_10bit": 0.0,
        "iqr_Av_QPBB_non-i": 0.0,
        "iqr_min_QP": 4.0,
        "kurtosis_Av_Motion": 9.740421405013588,
        "kurtosis_Av_QPBB_non-i": 0.0,
        "kurtosis_FrameSize_non-i": 16.14471942532962,
        "mean_Av_QPBB_non_i": 41.84398397787726,
        "predicted_mos_mode3_baseline": 3.490974452894264,
        "quant": 0.8204702740760247,
        "std_FrameSize_non-i": 1976.8673907210107,
        "std_max_QP_non-i": 1.1944582205351153,
        "vp9": 0.0
    },
    "per_second": [
        3.21337014105643,
        3.21337014105643,
        3.21337014105643,
        3.21337014105643,
        3.21337014105643,
        3.21337014105643,
        3.21337014105643,
        3.179819028977774
    ],
    "per_sequence": 3.21337014105643,
    "version": "0.1.2",
    "video_basename": "Chimera-EP01_8s_0-8000.avi_2160p_crf34_hevc.mkv",
    "video_full_path": "../../avt-bigdata/co_worker/rakesh/4k_viewing_distance_2/videosegments/Chimera-EP01_8s_0-8000.avi_2160p_crf34_hevc.mkv"
}