{
    "date": "2024-10-03 12:05:53.670751",
    "debug": {
        "baseline": 3.9424502658272162,
        "coding_deg": 30.06878650370362,
        "rf_pred": 4.135448197518642,
        "temporal_deg": 0.0,
        "upscaling_deg": 6.003029570567995
    },
    "features": {
        "0.0_quantil_StdDev_MotionX_non-i": 1.7104600911475718,
        "1.0_quantil_FrameSize": 118137.0,
        "Bitrate": 20888.7265625,
        "Framerate": 60.0,
        "Resolution": 3686400.0,
        "h264": 0.0,
        "h264_10bit": 0.0,
        "hevc": 1.0,
        "hevc_10bit": 0.0,
        "iqr_Av_QPBB_non-i": 2.0248013182134486,
        "iqr_min_QP": 2.0,
        "kurtosis_Av_Motion": 3.2314383776264046,
        "kurtosis_Av_QPBB_non-i": -0.5076606043926302,
        "kurtosis_FrameSize_non-i": -0.7541376539361537,
        "mean_Av_QPBB_non_i": 33.92161029418371,
        "predicted_mos_mode3_baseline": 3.9424502658272162,
        "quant": 0.6651296136114453,
        "std_FrameSize_non-i": 16796.340322398177,
        "std_max_QP_non-i": 1.2079161630269004,
        "vp9": 0.0
    },
    "per_second": [
        4.091080629097799,
        4.098532731912271,
        4.087511431537095,
        4.079418639344738,
        4.0094658725258885,
        3.9824874708881417,
        3.9573058964304457
    ],
    "per_sequence": 4.0389492316729285,
    "version": "0.1.2",
    "video_basename": "ElFuente_8s_224000-231750.avi_1440p_crf26_hevc.mkv",
    "video_full_path": "../../avt-bigdata/co_worker/rakesh/4k_viewing_distance_2/videosegments/ElFuente_8s_224000-231750.avi_1440p_crf26_hevc.mkv"
}